CHANGES.txt
CMakeLists.txt
COPYRIGHT.txt
INSTALL.txt
LICENSE.txt
MANIFEST.in
README.txt
setup.cfg
setup.py
examples/HelloWorld/HelloHandler.py
examples/HelloWorld/Message.py
examples/HelloWorld/Person.py
examples/HelloWorld/green.py
examples/HelloWorld/hello.py
examples/HelloWorld/hellov2.py
examples/HelloWorld/phold.py
examples/HelloWorld/cpp/HelloWorld/HelloHandlerInfo.h
examples/HelloWorld/cpp/HelloWorld/HelloHandlerPerson.C
examples/HelloWorld/cpp/HelloWorld/HelloHandlerPerson.h
examples/HelloWorld/cpp/HelloWorld/HelloWorld.C
examples/HelloWorld/cpp/HelloWorld/HelloWorld.h
examples/HelloWorld/cpp/HelloWorld/Person.C
examples/HelloWorld/cpp/HelloWorld/Person.h
examples/HelloWorld/cpp/HelloWorld/constants.h
examples/HelloWorld/cpp/HelloWorld/hello.cfg
examples/HelloWorld/cpp/HelloWorld/register.C
examples/HelloWorld/cpp/HelloWorld/types_HelloWorld.h
examples/HelloWorld/cpp/HelloWorld/TestData/info_HelloWorld.1.dat
examples/HelloWorld/cpp/HelloWorld/TestData/person_HelloWorld.dat
examples/HelloWorld/cpp/HelloWorld/TestData/service_HelloWorld.dat
examples/consensus/consensus.py
examples/countdown/cd.py
examples/countdown/cdkill.py
examples/os/ossim.py
simx/EventScheduler.py
simx/__init__.py
simx/config.py
simx/controller.py
simx/init.py
simx/process.py
simx/processmgr.py
simx/pyentity_ext.py
simx/resource.py
simx.egg-info/PKG-INFO
simx.egg-info/SOURCES.txt
simx.egg-info/dependency_links.txt
simx.egg-info/not-zip-safe
simx.egg-info/requires.txt
simx.egg-info/top_level.txt
simx/core/DebugStream.py
simx/core/OutputStream.py
simx/core/__init__.py
simx/core/core_ext.py
simx/core/util.py
simx/os/__init__.py
simx/os/node.py
simx/os/process.py
simx/os/processor.py
simx/os/system.py
src/minissf/BUGS
src/minissf/CMakeLists.txt
src/minissf/README
src/minissf/ssf-configure-check.txt
src/minissf/ssf.h
src/minissf/ssf_config.automake.h
src/minissf/ssf_config.automake.h.in
src/minissf/ssf_config.cmake.h.in
src/minissf/evtlist/binheap.h
src/minissf/evtlist/ladderq.h
src/minissf/evtlist/simevent.h
src/minissf/evtlist/splaytree.h
src/minissf/kernel/binque.cc
src/minissf/kernel/binque.h
src/minissf/kernel/kernel_event.cc
