Metadata-Version: 1.1
Name: simx
Version: 0.3.1
Summary: Parallel simulation library for Python
Home-page: http://simx.lanl.gov
Author: Sunil Thulasidasan, Lukas Kroc and others
Author-email: simx-dev@lanl.gov
License: GNU LGPL
Keywords: simulation,parallel simulation,distributed simulation,discrete event simulation,agent simulation,simulation library
Platform: GNU/Linux
Platform: Unix
Platform: Mac OS-X
Classifier: Development Status :: 4 - Beta
Classifier: Intended Audience :: Developers
Classifier: Intended Audience :: Science/Research
Classifier: License :: OSI Approved :: GNU Lesser General Public License v2 (LGPLv2)
Classifier: Operating System :: OS Independent
Classifier: Programming Language :: Python :: 2
Classifier: Programming Language :: Python :: 2.4
Classifier: Programming Language :: Python :: 2.5
Classifier: Programming Language :: Python :: 2.6
Classifier: Programming Language :: Python :: 2.7
Classifier: Topic :: Scientific/Engineering
Classifier: Topic :: Scientific/Engineering :: Artificial Life
Classifier: Topic :: Sociology
Classifier: Topic :: Software Development :: Libraries :: Python Modules
Classifier: Topic :: Software Development :: Libraries :: Application Frameworks
Classifier: Topic :: System :: Distributed Computing
Requires: greenlet
